m365auth.py
m365auth-0.2.2.dist-info/licenses/LICENSE
m365auth-0.2.2.dist-info/METADATA
m365auth-0.2.2.dist-info/WHEEL
m365auth-0.2.2.dist-info/entry_points.txt
m365auth-0.2.2.dist-info/top_level.txt
m365auth-0.2.2.dist-info/RECORD
