Metadata-Version: 2.4
Name: m365auth
Version: 0.2.2
Summary: OAuth2 authentication for Microsoft 365 services (IMAP/SMTP/Calendar/etc)
Requires-Python: >=3.6
License-File: LICENSE
Requires-Dist: msal
Requires-Dist: platformdirs
Requires-Dist: cryptography
Requires-Dist: keyring
Dynamic: license-file
